wandb/__init__.py
wandb/agent.py
wandb/api.py
wandb/cli.py
wandb/core.py
wandb/data_types.py
wandb/env.py
wandb/file_pusher.py
wandb/git_repo.py
wandb/history.py
wandb/internal_cli.py
wandb/io_wrap.py
wandb/jsonlfile.py
wandb/jupyter.py
wandb/media.py
wandb/meta.py
wandb/retry.py
wandb/run_manager.py
wandb/rwlock.py
wandb/sparkline.py
wandb/stats.py
wandb/streaming_log.py
wandb/summary.py
wandb/typedtable.py
wandb/util.py
wandb/wandb_config.py
wandb/wandb_keras.py
wandb/wandb_run.py
wandb/wandb_socket.py
wandb/wandb_tensorflow.py
wandb/wandb_torch.py
wandb/wandb_types.py
wandb/board/ui/build/.DS_Store
wandb/board/ui/build/report.html
wandb/keras/__init__.py
wandb_testing-0.6.1.post1.dist-info/DESCRIPTION.rst
wandb_testing-0.6.1.post1.dist-info/METADATA
wandb_testing-0.6.1.post1.dist-info/RECORD
wandb_testing-0.6.1.post1.dist-info/WHEEL
wandb_testing-0.6.1.post1.dist-info/entry_points.txt
wandb_testing-0.6.1.post1.dist-info/metadata.json
wandb_testing-0.6.1.post1.dist-info/top_level.txt
