Metadata-Version: 2.0
Name: wandb-testing
Version: 0.6.1.post1
Summary: A CLI and library for interacting with the Weights and Biases API.
Home-page: https://github.com/wandb/client
Author: Weights & Biases
Author-email: support@wandb.com
License: MIT license
Keywords: wandb
Platform: UNKNOWN
Classifier: Development Status :: 2 - Pre-Alpha
Classifier: Intended Audience :: Developers
Classifier: License :: OSI Approved :: MIT License
Classifier: Natural Language :: English
Classifier: Programming Language :: Python :: 2
Classifier: Programming Language :: Python :: 2.6
Classifier: Programming Language :: Python :: 2.7
Classifier: Programming Language :: Python :: 3
Classifier: Programming Language :: Python :: 3.3
Classifier: Programming Language :: Python :: 3.4
Classifier: Programming Language :: Python :: 3.5
Requires-Dist: Click (>=6.0)
Requires-Dist: GitPython (>=1.0.0)
Requires-Dist: gql (>=0.1.0)
Requires-Dist: nvidia-ml-py3 (>=7.352.0)
Requires-Dist: psutil (>=5.2.2)
Requires-Dist: python-dateutil (>=2.6.1)
Requires-Dist: requests (>=2.0.0)
Requires-Dist: shortuuid (>=0.5.0)
Requires-Dist: six (>=1.10.0)
Requires-Dist: watchdog (>=0.8.3)
Requires-Dist: whaaaaat (>=0.5.2)
